nonebot_plugin_pjsk_helper-1.1.0.dist-info/METADATA
nonebot_plugin_pjsk_helper-1.1.0.dist-info/WHEEL
nonebot_plugin_pjsk_helper-1.1.0.dist-info/entry_points.txt
nonebot_plugin_pjsk_helper-1.1.0.dist-info/licenses/LICENSE
nonebot_plugin_pjsk_helper/__init__.py
nonebot_plugin_pjsk_helper/__main__.py
nonebot_plugin_pjsk_helper/character_data_get.py
nonebot_plugin_pjsk_helper/config.py
nonebot_plugin_pjsk_helper/data/help.png
nonebot_plugin_pjsk_helper/data/pjsk_character.json
nonebot_plugin_pjsk_helper/data/pjsk_music.json
nonebot_plugin_pjsk_helper/music_data_get.py
nonebot_plugin_pjsk_helper/music_find.py
nonebot_plugin_pjsk_helper-1.1.0.dist-info/RECORD
