Metadata-Version: 2.1
Name: nonebot-plugin-pjsk-helper
Version: 1.1.0
Summary: Default template for PDM package
Author-Email: Atr1ck <3126670240@qq.com>
License: MIT
Requires-Python: >=3.9
Requires-Dist: beautifulsoup4>=4.12.3
Requires-Dist: nonebot2>=2.3.3
Requires-Dist: nonebot-adapter-onebot>=2.4.5
Requires-Dist: lxml>=5.3.0
Requires-Dist: playwright>=1.47.0
Requires-Dist: pyproject-toml>=0.0.10
